mbhupdater/__init__.py
mbhupdater/tqdm_updater.py
mbhupdater/updater.py
mbhupdater-0.1.0.dist-info/LICENSE
mbhupdater-0.1.0.dist-info/METADATA
mbhupdater-0.1.0.dist-info/WHEEL
mbhupdater-0.1.0.dist-info/top_level.txt
mbhupdater-0.1.0.dist-info/RECORD
