Metadata-Version: 2.1
Name: mbhupdater
Version: 0.1.0
Summary: An easy-to-use, OS-Independent updater for games/programs.
Home-page: https://github.com/MysteryBlokHed/mbhupdater
Author: Adam Thompson-Sharpe
Author-email: adamthompsonsharpe@gmail.com
License: Unlicense
Platform: UNKNOWN
Classifier: Programming Language :: Python :: 3.6
Classifier: License :: Public Domain
Classifier: Operating System :: OS Independent
Requires-Dist: tqdm
